xiaoranli/__init__.py
xiaoranli/data/rc_files/alias
xiaoranli/data/rc_files/dockerignore
xiaoranli/data/rc_files/gdbinit
xiaoranli/data/rc_files/gitconfig
xiaoranli/data/rc_files/inputrc
xiaoranli/data/rc_files/tmux.config
xiaoranli/data/rc_files/vimrc
xiaoranli/scripts/install_golang.sh
xiaoranli/scripts/install_useful_tools.sh
xiaoranli/scripts/install_zsh.sh
xiaoranli/scripts/install_zsh_extensions.sh
xiaoranli/zhijiang/scripts/enhance_python.sh
xiaoranli/zhijiang/scripts/install_useful_tools.sh
xiaoranli/zhijiang/scripts/useful_func.py
xiaoranli-7.2.2.dist-info/LICENSE.txt
xiaoranli-7.2.2.dist-info/METADATA
xiaoranli-7.2.2.dist-info/WHEEL
xiaoranli-7.2.2.dist-info/entry_points.txt
xiaoranli-7.2.2.dist-info/top_level.txt
xiaoranli-7.2.2.dist-info/RECORD
